karantools/__init__.py
karantools/tests/__init__.py
karantools/tests/benchmark_concurrency.py
karantools/tests/test_karantools.py
karantools-0.1.8.dist-info/METADATA
karantools-0.1.8.dist-info/WHEEL
karantools-0.1.8.dist-info/top_level.txt
karantools-0.1.8.dist-info/RECORD
