Metadata-Version: 2.1
Name: karantools
Version: 0.1.8
Summary: Karan's useful Python utilities.
Home-page: http://github.com/karan1149/karantools
Author: Karan Singhal
Author-email: karan1149@gmail.com
License: MIT
Keywords: tools utils utilities toolkit
Platform: UNKNOWN
